odoo9_addon_stock_available-9.0.1.1.0.99.dev27-py3.8-nspkg.pth
odoo_addons/stock_available/README.rst
odoo_addons/stock_available/__init__.py
odoo_addons/stock_available/__openerp__.py
odoo_addons/stock_available/i18n/ca.po
odoo_addons/stock_available/i18n/de.po
odoo_addons/stock_available/i18n/el_GR.po
odoo_addons/stock_available/i18n/es.po
odoo_addons/stock_available/i18n/es_ES.po
odoo_addons/stock_available/i18n/es_MX.po
odoo_addons/stock_available/i18n/eu.po
odoo_addons/stock_available/i18n/fi.po
odoo_addons/stock_available/i18n/fr.po
odoo_addons/stock_available/i18n/fr_CH.po
odoo_addons/stock_available/i18n/fr_FR.po
odoo_addons/stock_available/i18n/gl.po
odoo_addons/stock_available/i18n/hr.po
odoo_addons/stock_available/i18n/hr_HR.po
odoo_addons/stock_available/i18n/it.po
odoo_addons/stock_available/i18n/nl.po
odoo_addons/stock_available/i18n/nl_NL.po
odoo_addons/stock_available/i18n/pt.po
odoo_addons/stock_available/i18n/pt_BR.po
odoo_addons/stock_available/i18n/ro.po
odoo_addons/stock_available/i18n/ru.po
odoo_addons/stock_available/i18n/sk.po
odoo_addons/stock_available/i18n/sl.po
odoo_addons/stock_available/i18n/stock_available.pot
odoo_addons/stock_available/i18n/tr.po
odoo_addons/stock_available/i18n/tr_TR.po
odoo_addons/stock_available/i18n/vi_VN.po
odoo_addons/stock_available/i18n/zh_CN.po
odoo_addons/stock_available/models/__init__.py
odoo_addons/stock_available/models/product_product.py
odoo_addons/stock_available/models/product_template.py
odoo_addons/stock_available/models/res_config.py
odoo_addons/stock_available/static/description/icon.png
odoo_addons/stock_available/views/product_product_view.xml
odoo_addons/stock_available/views/product_template_view.xml
odoo_addons/stock_available/views/res_config_view.xml
odoo9_addon_stock_available-9.0.1.1.0.99.dev27.dist-info/METADATA
odoo9_addon_stock_available-9.0.1.1.0.99.dev27.dist-info/WHEEL
odoo9_addon_stock_available-9.0.1.1.0.99.dev27.dist-info/namespace_packages.txt
odoo9_addon_stock_available-9.0.1.1.0.99.dev27.dist-info/top_level.txt
odoo9_addon_stock_available-9.0.1.1.0.99.dev27.dist-info/RECORD
